{
    "title": "¡Mis Habilidades!",
    "slug": "habilidades",
    "descripcion": "Poseo experiencia utilizando las siguientes tecnologías..",
    "items": [
        {
            "name": "PHP",
            "desc": ""
        },
        {
            "name": "JAVASCRIPT",
            "desc": ""
        },
        {
            "name": "NODEJS",
            "desc": "API-REST - JWT"
        },
        {
            "name": "REACT",
            "desc": "REACT-ROUTER - REDUX - GATSBY - NEXTJS"
        },
        {
            "name": "VUE",
            "desc": ""
        },
        {
            "name": "LARAVEL",
            "desc": "API-REST - PASSPORT - DESARROLLO WEB EN GENERAL"
        },
        {
            "name": "BASES DE DATOS(Mysql - Oracle - MongoDB)",
            "desc": ""
        },
        {
            "name": "GIT",
            "desc": ""
        },
        {
            "name": "REACT NATIVE",
            "desc": "DESARROLLO DE APLICACIONES MOVILES"
        }
    ]
}